Workbook

Sheet README
A1: Test Cases Regole v2 — FantaDuma Manageriale App
A3: Versione | B3: 2.0 — 07/07/2026
A4: Fonte | B4: Regolamento e Statuto Fanta Duma 2025.26 + 02_Regole_Economiche_RulesEngine.md (v4.0)
A5: Sostituisce | B5: 09_Test_Cases_Regole (ChatGPT): i casi basati su quote arbitrarie 100/80/60/40/20 NON sono validi
A6: Scopo | B6: Casi che il rules engine deve far passare prima del go-live. Ogni TC referenzia la sezione del doc 02
A7: Uso | B7: Lo sviluppatore compila Actual Result; lo Status si aggiorna da solo (Pass/Fail/Da testare)
A8: Tipi di test | B8: CALCOLO = verifica valore numerico | BLOCCO = il sistema deve impedire | STATO = transizione/effetti | INVARIANTE = proprietà sempre vera
A9: Priorità | B9: Must = bloccante per go-live | Should = alta | Could = rifinitura
A10: Convenzioni | B10: Importi in € = ingaggi/multe (soldi veri). Importi in crediti = valuta virtuale di mercato. Mai confonderli (doc 02 §1)

Sheet Test_Cases
A1: ID | B1: Area | C1: Rif. doc 02 | D1: Tipo | E1: Priorità | F1: Scenario | G1: Precondizioni / Input | H1: Azione | I1: Risultato atteso | J1: Actual Result | K1: Status
A2: TC-001 | B2: Doppia valuta | C2: §1 | D2: INVARIANTE | E2: Must | F2: Crediti ed euro mai mescolati | G2: Qualsiasi operazione di mercato | H2: Eseguire acquisto, svincolo e scambio | I2: Ogni movimento è registrato o nel ledger crediti o nel ledger euro; nessuna scrittura incrociata; nessuna conversione | K2: =IF(J2="","Da testare",IF(EXACT(TRIM(J2),"OK"),"Pass","Fail")) -> Da testare
A3: TC-002 | B3: Doppia valuta | C3: §1 | D3: CALCOLO | E3: Must | F3: Acquisto scala solo crediti | G3: Squadra con budget 500 crediti; giocatore aggiudicato a 80 crediti | H3: Confermare acquisto | I3: Budget crediti 420; contabilità euro invariata (solo il nuovo ingaggio a bilancio ingaggi) | K3: =IF(J3="","Da testare",IF(EXACT(TRIM(J3),"OK"),"Pass","Fail")) -> Da testare
A4: TC-003 | B4: Ingaggi | C4: §2 | D4: CALCOLO | E4: Must | F4: Ingaggio STD da FVM M (esempio regolamento) | G4: FVM M congelato = 155 | H4: Creare contratto Standard | I4: Ingaggio = 15,50 € (10% arrotondato per eccesso a 0,50) | K4: =IF(J4="","Da testare",IF(EXACT(TRIM(J4),"OK"),"Pass","Fail")) -> Da testare
A5: TC-004 | B5: Ingaggi | C5: §2 | D5: CALCOLO | E5: Must | F5: Arrotondamento per eccesso | G5: FVM M = 151 | H5: Creare contratto Standard | I5: Ingaggio = 15,50 € (15,1 → eccesso a 0,50) | K5: =IF(J5="","Da testare",IF(EXACT(TRIM(J5),"OK"),"Pass","Fail")) -> Da testare
A6: TC-005 | B6: Ingaggi | C6: §2 | D6: CALCOLO | E6: Must | F6: Nessun arrotondamento se già multiplo di 0,50 | G6: FVM M = 150 | H6: Creare contratto Standard | I6: Ingaggio = 15,00 € | K6: =IF(J6="","Da testare",IF(EXACT(TRIM(J6),"OK"),"Pass","Fail")) -> Da testare
A7: TC-006 | B7: Ingaggi | C7: §2 | D7: CALCOLO | E7: Must | F7: Minimo salariale | G7: FVM M = 3 | H7: Creare contratto Standard | I7: Ingaggio = 0,50 € (minimo, non 0,30) | K7: =IF(J7="","Da testare",IF(EXACT(TRIM(J7),"OK"),"Pass","Fail")) -> Da testare
A8: TC-007 | B8: Ingaggi | C8: §2 | D8: CALCOLO | E8: Must | F8: Ingaggio indipendente dal prezzo d'asta | G8: FVM M = 100; giocatore pagato 250 crediti all'asta | H8: Creare contratto Standard | I8: Ingaggio = 10,00 € (legato al FVM M, non ai 250 crediti) | K8: =IF(J8="","Da testare",IF(EXACT(TRIM(J8),"OK"),"Pass","Fail")) -> Da testare
A9: TC-008 | B9: Ingaggi | C9: §2 | D9: CALCOLO | E9: Must | F9: Obbligo 1+1 — maggiorazione | G9: FVM M = 100; contratto Obbligo 1+1 | H9: Calcolare piano ingaggi | I9: Anno 1 = 11,50 €; Anno 2 = 11,50 € (+15% / +15%) | K9: =IF(J9="","Da testare",IF(EXACT(TRIM(J9),"OK"),"Pass","Fail")) -> Da testare
A10: TC-009 | B10: Ingaggi | C10: §2 | D10: CALCOLO | E10: Must | F10: Obbligo 1+2 — terzo anno al 10% | G10: FVM M = 100; contratto Obbligo 1+2 | H10: Calcolare piano ingaggi | I10: 11,50 / 11,50 / 11,00 € (+15/+15/+10, sempre su FVM congelato) | K10: =IF(J10="","Da testare",IF(EXACT(TRIM(J10),"OK"),"Pass","Fail")) -> Da testare
A11: TC-010 | B11: Ingaggi | C11: §2 | D11: CALCOLO | E11: Must | F11: Diritto 1+1 — maggiorazione 30% | G11: FVM M = 100; contratto Diritto 1+1 | H11: Calcolare piano ingaggi | I11: 13,00 € anno 1; 13,00 € anno 2 se riscattato | K11: =IF(J11="","Da testare",IF(EXACT(TRIM(J11),"OK"),"Pass","Fail")) -> Da testare
A12: TC-011 | B12: Ingaggi | C12: §2 | D12: CALCOLO | E12: Must | F12: Contratto invernale — primo anno dimezzato (esempio regolamento) | G12: FVM M = 100; acquisto asta riparazione; Obbligo 0,5+2 | H12: Calcolare piano ingaggi | I12: Anno 1 = 6,50 € (½ STD +15%); Anno 2 = 11,50 €; Anno 3 = 11,00 € | K12: =IF(J12="","Da testare",IF(EXACT(TRIM(J12),"OK"),"Pass","Fail")) -> Da testare
A13: TC-012 | B13: Ingaggi | C13: §2 | D13: CALCOLO | E13: Must | F13: FVM congelato per tutta la durata | G13: FVM M all'asta = 100; a gennaio il FVM M sale a 180 | H13: Ricalcolare ingaggi anno 2 di un Obbligo 1+1 | I13: Ingaggio resta 11,50 € (base congelata 100, non 180) | K13: =IF(J13="","Da testare",IF(EXACT(TRIM(J13),"OK"),"Pass","Fail")) -> Da testare
... A85: TC-084 | B85: Migrazione | C85: doc 03 | D85: CALCOLO | E85: Must | F85: Quadratura post-import | G85: Import iniziale dal GESTIONALE_UFFICIALE completato | H85: Confrontare app vs foglio | I85: Budget crediti, monte ingaggi e conteggio slot IDENTICI al foglio per tutte le 10 squadre, prima del go-live | K85: =IF(J85="","Da testare",IF(EXACT(TRIM(J85),"OK"),"Pass","Fail")) -> Da testare

Sheet Coverage
A1: Sezione doc 02 | B1: Tema | C1: N. test case | D1: Must | E1: Note
A2: §1 | B2: Doppia valuta crediti/euro | C2: =COUNTIF(Test_Cases!C:C,"*§1*") -> 16 | D2: =COUNTIFS(Test_Cases!C:C,"*§1*",Test_Cases!E:E,"Must") -> 12
A3: §2 | B3: Ingaggi e maggiorazioni | C3: =COUNTIF(Test_Cases!C:C,"*§2*") -> 12 | D3: =COUNTIFS(Test_Cases!C:C,"*§2*",Test_Cases!E:E,"Must") -> 12
A4: §3 | B4: Salary cap | C4: =COUNTIF(Test_Cases!C:C,"*§3*") -> 5 | D4: =COUNTIFS(Test_Cases!C:C,"*§3*",Test_Cases!E:E,"Must") -> 4
A5: §4 | B5: Slot e limiti rosa | C5: =COUNTIF(Test_Cases!C:C,"*§4*") -> 10 | D5: =COUNTIFS(Test_Cases!C:C,"*§4*",Test_Cases!E:E,"Must") -> 10
A6: §5 | B6: Finestre e ammortamento | C6: =COUNTIF(Test_Cases!C:C,"*§5*") -> 8 | D6: =COUNTIFS(Test_Cases!C:C,"*§5*",Test_Cases!E:E,"Must") -> 6
A7: §6 | B7: Svincoli | C7: =COUNTIF(Test_Cases!C:C,"*§6*") -> 11 | D7: =COUNTIFS(Test_Cases!C:C,"*§6*",Test_Cases!E:E,"Must") -> 10
A8: §7 | B8: Formula STIMA | C8: =COUNTIF(Test_Cases!C:C,"*§7*") -> 4 | D8: =COUNTIFS(Test_Cases!C:C,"*§7*",Test_Cases!E:E,"Must") -> 3
A9: §8 | B9: Asteriscati e Osimhen Gate | C9: =COUNTIF(Test_Cases!C:C,"*§8*") -> 7 | D9: =COUNTIFS(Test_Cases!C:C,"*§8*",Test_Cases!E:E,"Must") -> 5
A10: §9 | B10: Vivaio | C10: =COUNTIF(Test_Cases!C:C,"*§9*") -> 11 | D10: =COUNTIFS(Test_Cases!C:C,"*§9*",Test_Cases!E:E,"Must") -> 9
A11: §10 | B11: Aste | C11: =COUNTIF(Test_Cases!C:C,"*§10*") -> 3 | D11: =COUNTIFS(Test_Cases!C:C,"*§10*",Test_Cases!E:E,"Must") -> 1
A12: §11 | B12: Multe e contabilità euro | C12: =COUNTIF(Test_Cases!C:C,"*§11*") -> 3 | D12: =COUNTIFS(Test_Cases!C:C,"*§11*",Test_Cases!E:E,"Must") -> 2
A13: §12 | B13: Workflow e invarianti | C13: =COUNTIF(Test_Cases!C:C,"*§12*") -> 8 | D13: =COUNTIFS(Test_Cases!C:C,"*§12*",Test_Cases!E:E,"Must") -> 7
A14: doc 03 | B14: Migrazione | C14: =COUNTIF(Test_Cases!C:C,"doc 03") -> 1 | D14: =COUNTIFS(Test_Cases!C:C,"doc 03",Test_Cases!E:E,"Must") -> 1
B15: TOTALE | C15: =SUM(C2:C14) -> 99 | D15: =SUM(D2:D14) -> 82

Sheet Summary
A1: Metrica | B1: Valore
A2: Totale test case | B2: =COUNTA(Test_Cases!A2:A85) -> 84
A3: Must | B3: =COUNTIF(Test_Cases!E2:E85,"Must") -> 71
A4: Should | B4: =COUNTIF(Test_Cases!E2:E85,"Should") -> 13
A5: Pass | B5: =COUNTIF(Test_Cases!K2:K85,"Pass") -> 0
A6: Fail | B6: =COUNTIF(Test_Cases!K2:K85,"Fail") -> 0
A7: Da testare | B7: =COUNTIF(Test_Cases!K2:K85,"Da testare") -> 84
A8: Must passati | B8: =COUNTIFS(Test_Cases!E2:E85,"Must",Test_Cases!K2:K85,"Pass") -> 0
A9: Go-live ready (tutti i Must Pass) | B9: =IF(B8=B3,"SI","NO") -> NO
